ape/__init__.py
ape/_cli.py
ape/exceptions.py
ape/harambe.py
ape/logging.py
ape/py.typed
ape/version.py
ape/api/__init__.py
ape/api/accounts.py
ape/api/address.py
ape/api/compiler.py
ape/api/config.py
ape/api/convert.py
ape/api/explorers.py
ape/api/networks.py
ape/api/projects.py
ape/api/providers.py
ape/api/query.py
ape/api/trace.py
ape/api/transactions.py
ape/cli/__init__.py
ape/cli/arguments.py
ape/cli/choices.py
ape/cli/commands.py
ape/cli/options.py
ape/cli/paramtype.py
ape/contracts/__init__.py
ape/contracts/base.py
ape/managers/__init__.py
ape/managers/_contractscache.py
ape/managers/_deploymentscache.py
ape/managers/accounts.py
ape/managers/base.py
ape/managers/chain.py
ape/managers/compilers.py
ape/managers/config.py
ape/managers/converters.py
ape/managers/networks.py
ape/managers/plugins.py
ape/managers/project.py
ape/managers/query.py
ape/plugins/__init__.py
ape/plugins/_utils.py
ape/plugins/account.py
ape/plugins/compiler.py
ape/plugins/config.py
ape/plugins/converter.py
ape/plugins/network.py
ape/plugins/pluggy_patch.py
ape/plugins/project.py
ape/plugins/query.py
ape/pytest/README.md
ape/pytest/__init__.py
ape/pytest/config.py
ape/pytest/contextmanagers.py
ape/pytest/coverage.py
ape/pytest/fixtures.py
ape/pytest/gas.py
ape/pytest/plugin.py
ape/pytest/runners.py
ape/pytest/utils.py
ape/pytest/warnings.py
ape/types/__init__.py
ape/types/address.py
ape/types/basic.py
ape/types/coverage.py
ape/types/events.py
ape/types/gas.py
ape/types/private_mempool.py
ape/types/signatures.py
ape/types/trace.py
ape/types/units.py
ape/types/vm.py
ape/utils/__init__.py
ape/utils/_github.py
ape/utils/abi.py
ape/utils/basemodel.py
ape/utils/misc.py
ape/utils/os.py
ape/utils/process.py
ape/utils/rpc.py
ape/utils/testing.py
ape/utils/trace.py
ape/utils/validators.py
ape_accounts/__init__.py
ape_accounts/_cli.py
ape_accounts/accounts.py
ape_accounts/py.typed
ape_cache/__init__.py
ape_cache/_cli.py
ape_cache/base.py
ape_cache/config.py
ape_cache/models.py
ape_cache/py.typed
eth_ape-0.8.47.dist-info/licenses/LICENSE
eth_ape-0.8.47.dist-info/METADATA
eth_ape-0.8.47.dist-info/WHEEL
eth_ape-0.8.47.dist-info/entry_points.txt
eth_ape-0.8.47.dist-info/top_level.txt
eth_ape-0.8.47.dist-info/RECORD
