Metadata-Version: 2.4
Name: eth-ape
Version: 0.8.47
Summary: Ape Framework: Build and explore on-chain with Python
Author-email: "ApeWorX Ltd." <admin@apeworx.io>
License-Expression: Apache-2.0
Project-URL: Homepage, https://apeworx.io/framework
Project-URL: Repository, https://github.com/ApeWorX/ape.git
Project-URL: Issues, https://github.com/ApeWorX/ape/issues
Project-URL: Documentation, https://docs.apeworx.io/ape/stable
Project-URL: Funding, https://github.com/sponsors/ApeWorX
Project-URL: Twitter / X, https://x.com/ApeFramework
Keywords: ape,crypto,ethereum,devtool,defi,nft
Classifier: Development Status :: 5 - Production/Stable
Classifier: Intended Audience :: Developers
Classifier: Natural Language :: English
Classifier: Operating System :: MacOS
Classifier: Operating System :: POSIX
Classifier: Operating System :: Microsoft :: Windows
Classifier: Programming Language :: Python :: 3
Classifier: Programming Language :: Python :: 3.10
Classifier: Programming Language :: Python :: 3.11
Classifier: Programming Language :: Python :: 3.12
Classifier: Programming Language :: Python :: 3.13
Classifier: Programming Language :: Python :: 3.14
Requires-Python: <4,>=3.10
License-File: LICENSE
Requires-Dist: click<8.2,>=8.1.6
Requires-Dist: ijson<4,>=3.1.4
Requires-Dist: ipython<9,>=8.18.1
Requires-Dist: lazyasd>=0.1.4
Requires-Dist: asttokens<3,>=2.4.1
Requires-Dist: cchecksum<1,>=0.0.3
Requires-Dist: numpy<2
Requires-Dist: packaging<24,>=23.0
Requires-Dist: pandas<3,>=2.2.2
Requires-Dist: pluggy<2,>=1.3
Requires-Dist: pydantic<3,>=2.10
Requires-Dist: pydantic-settings<3,>=2.5.2
Requires-Dist: pytest<9.0,>=8.0
Requires-Dist: python-dateutil<3,>=2.8.2
Requires-Dist: PyYAML<7,>=5.1
Requires-Dist: requests<3,>=2.28.1
Requires-Dist: rich<14,>=13.9
Requires-Dist: SQLAlchemy>=1.4.35
Requires-Dist: toml; python_version < "3.11"
Requires-Dist: tqdm<5.0,>=4.67
Requires-Dist: traitlets>=5.3.0
Requires-Dist: urllib3<3,>=2.3
Requires-Dist: watchdog<4,>=3.0
Requires-Dist: eth-abi<6,>=5.1.0
Requires-Dist: eth-account<0.14,>=0.11.3
Requires-Dist: eth-typing<6,>=3.5.2
Requires-Dist: eth-utils<6,>=2.1.0
Requires-Dist: hexbytes<2,>=1.2.0
Requires-Dist: py-geth<7,>=6.2.0
Requires-Dist: trie<4,>=3.0.1
Requires-Dist: web3[tester]<8,>=7.12.1
Requires-Dist: ethpm-types<0.7,>=0.6.28
Requires-Dist: eip712<0.4,>=0.3.0
Requires-Dist: eth_pydantic_types<0.3,>=0.2.1
Requires-Dist: evmchains<0.2,>=0.1.0
Requires-Dist: evm-trace<0.3,>=0.2.6
Provides-Extra: recommended-plugins
Requires-Dist: ape-alchemy; extra == "recommended-plugins"
Requires-Dist: ape-ens; extra == "recommended-plugins"
Requires-Dist: ape-etherscan; extra == "recommended-plugins"
Requires-Dist: ape-foundry; extra == "recommended-plugins"
Requires-Dist: ape-hardhat; extra == "recommended-plugins"
Requires-Dist: ape-infura; extra == "recommended-plugins"
Requires-Dist: ape-solidity; extra == "recommended-plugins"
Requires-Dist: ape-template; extra == "recommended-plugins"
Requires-Dist: ape-tokens; extra == "recommended-plugins"
Requires-Dist: ape-vyper; extra == "recommended-plugins"
Dynamic: license-file
